lexman_ble/__init__.py
lexman_ble/cct_smart_bulb.py
lexman_ble/const.py
lexman_ble/exceptions.py
lexman_ble/models.py
lexman_ble-0.1.0.dist-info/LICENSE
lexman_ble-0.1.0.dist-info/METADATA
lexman_ble-0.1.0.dist-info/WHEEL
lexman_ble-0.1.0.dist-info/RECORD
