Metadata-Version: 2.1
Name: lexman-ble
Version: 0.1.0
Summary: Lexman CCT Smart Bulb control through bluetooth in Python
Author: davidsmfreire
Author-email: davidsmfreire@gmail.com
Requires-Python: >=3.12.0,<3.13
Classifier: Programming Language :: Python :: 3
Classifier: Programming Language :: Python :: 3.12
Requires-Dist: bleak (>=0.19.0)
Requires-Dist: bleak-retry-connector (>=2.3.0)
Requires-Dist: bluetooth-data-tools (==1.20.0)
Requires-Dist: parse (>=1.20.2,<2.0.0)
